meta_subject/__init__.py
meta_subject/action_items.py
meta_subject/admin_site.py
meta_subject/apps.py
meta_subject/choices.py
meta_subject/constants.py
meta_subject/identifiers.py
meta_subject/mommy_recipes.py
meta_subject/urls.py
meta_subject/admin/__init__.py
meta_subject/admin/complications_admin.py
meta_subject/admin/followup_admin.py
meta_subject/admin/followup_vitals_admin.py
meta_subject/admin/health_economics_admin.py
meta_subject/admin/malaria_test_admin.py
meta_subject/admin/medication_adherence_admin.py
meta_subject/admin/modeladmin.py
meta_subject/admin/patient_history_admin.py
meta_subject/admin/physical_exam_admin.py
meta_subject/admin/subject_requisition_admin.py
meta_subject/admin/subject_visit_admin.py
meta_subject/admin/urine_dipstick_test_admin.py
meta_subject/admin/blood_results/__init__.py
meta_subject/admin/blood_results/blood_results_fbc_admin.py
meta_subject/admin/blood_results/blood_results_glu_admin.py
meta_subject/admin/blood_results/blood_results_hba1c_admin.py
meta_subject/admin/blood_results/blood_results_lft_admin.py
meta_subject/admin/blood_results/blood_results_lipid_admin.py
meta_subject/admin/blood_results/blood_results_modeladmin_mixin.py
meta_subject/admin/blood_results/blood_results_rft_admin.py
meta_subject/forms/__init__.py
meta_subject/forms/followup_form.py
meta_subject/forms/followup_vitals_form.py
meta_subject/forms/form_mixins.py
meta_subject/forms/malaria_test_form.py
meta_subject/forms/medication_adherence_form.py
meta_subject/forms/patient_history_form.py
meta_subject/forms/physical_exam_form.py
meta_subject/forms/slider_widget.py
meta_subject/forms/subject_requisition_form.py
meta_subject/forms/subject_visit_form.py
meta_subject/forms/urine_dipstick_test_form.py
meta_subject/forms/blood_results/__init__.py
meta_subject/forms/blood_results/blood_results_fbc_form.py
meta_subject/forms/blood_results/blood_results_glu_form.py
meta_subject/forms/blood_results/blood_results_hba1c_form.py
meta_subject-0.1.25.dist-info/AUTHORS
meta_subject-0.1.25.dist-info/LICENSE
meta_subject-0.1.25.dist-info/METADATA
meta_subject-0.1.25.dist-info/WHEEL
meta_subject-0.1.25.dist-info/top_level.txt
meta_subject-0.1.25.dist-info/RECORD
